setup.py
chaitu_distributions/Binomialdistribution.py
chaitu_distributions/Gaussiandistribution.py
chaitu_distributions/Generaldistribution.py
chaitu_distributions/__init__.py
chaitu_distributions.egg-info/PKG-INFO
chaitu_distributions.egg-info/SOURCES.txt
chaitu_distributions.egg-info/dependency_links.txt
chaitu_distributions.egg-info/not-zip-safe
chaitu_distributions.egg-info/top_level.txt