Metadata-Version: 1.0
Name: chaitu-distributions
Version: 0.1
Summary: Gaussian distributions
Home-page: UNKNOWN
Author: chaitanya_basava
Author-email: viswachaitanya.b16@iiits.in
License: UNKNOWN
Platform: UNKNOWN
